authentication/AzureAdAuthentication.py
authentication/GraphApiClient.py
authentication/GraphApiModel.py
authentication/IAuthProvider.py
authentication/__init__.py
authentication/decorators.py
authentication/exceptions.py
authentication/serializers.py
authentication/tests.py
authentication/utils.py
compliancex_auth-1.0.dist-info/METADATA
compliancex_auth-1.0.dist-info/WHEEL
compliancex_auth-1.0.dist-info/top_level.txt
compliancex_auth-1.0.dist-info/RECORD
